colorem/__init__.py
colorem/_version.py
colorem/classes.py
colorem/setup.py
colorem-0.1.0.dist-info/LICENSE.txt
colorem-0.1.0.dist-info/METADATA
colorem-0.1.0.dist-info/WHEEL
colorem-0.1.0.dist-info/top_level.txt
colorem-0.1.0.dist-info/RECORD
