Metadata-Version: 2.1
Name: colorem
Version: 0.1.0
Summary: COLOR mEets Munsell
Author-email: Adolfo Molada Tebar <a.molada.tebar@gmail.com>
Classifier: Programming Language :: Python :: 3.8
Classifier: License :: OSI Approved :: GNU General Public License v3 (GPLv3)
Classifier: Operating System :: OS Independent
Requires-Python: >=3.8
License-File: LICENSE.txt
